librehtf/__init__.py
librehtf/auth.py
librehtf/db.py
librehtf/evaluate.py
librehtf/manage.py
librehtf/schema.sql
librehtf/api/device.py
librehtf/api/task.py
librehtf/api/test.py
librehtf/api/user.py
librehtf/static/site.css
librehtf/templates/404.html
librehtf/templates/base.html
librehtf/templates/evaluate.html
librehtf/templates/index.html
librehtf/templates/manage.html
librehtf/templates/auth/login.html
librehtf/templates/auth/token.html
librehtf/templates/evaluate/results.html
librehtf/templates/manage/create_device.html
librehtf/templates/manage/create_task.html
librehtf/templates/manage/create_test.html
librehtf/templates/manage/create_user.html
librehtf/templates/manage/update_device.html
librehtf/templates/manage/update_task.html
librehtf/templates/manage/update_test.html
librehtf/templates/manage/update_user.html
tests/__init__.py
tests/preload.sql
tests/test_auth.py
tests/test_device.py
tests/test_init.py
tests/test_task.py
tests/test_test.py
tests/test_user.py
librehtf-0.0.3.dist-info/LICENSE
librehtf-0.0.3.dist-info/METADATA
librehtf-0.0.3.dist-info/WHEEL
librehtf-0.0.3.dist-info/top_level.txt
librehtf-0.0.3.dist-info/RECORD
